plasoscaffolder/.style.yapf
plasoscaffolder/__init__.py
plasoscaffolder/dependencies.py
plasoscaffolder/bll/__init__.py
plasoscaffolder/bll/mappings/__init__.py
plasoscaffolder/bll/mappings/base_mapping_helper.py
plasoscaffolder/bll/mappings/base_sqliteplugin_mapping.py
plasoscaffolder/bll/mappings/formatter_init_mapping.py
plasoscaffolder/bll/mappings/formatter_mapping.py
plasoscaffolder/bll/mappings/formatter_test_mapping.py
plasoscaffolder/bll/mappings/mapping_helper.py
plasoscaffolder/bll/mappings/parser_init_mapping.py
plasoscaffolder/bll/mappings/parser_mapping.py
plasoscaffolder/bll/mappings/parser_test_mapping.py
plasoscaffolder/bll/services/__init__.py
plasoscaffolder/bll/services/base_sqlite_generator.py
plasoscaffolder/bll/services/base_sqlite_plugin_helper.py
plasoscaffolder/bll/services/base_sqlite_plugin_path_helper.py
plasoscaffolder/bll/services/sqlite_generator.py
plasoscaffolder/bll/services/sqlite_plugin_helper.py
plasoscaffolder/bll/services/sqlite_plugin_path_helper.py
plasoscaffolder/bll/templates/__init__.py
plasoscaffolder/bll/templates/formatter_init_template.jinja2
plasoscaffolder/bll/templates/formatter_template.jinja2
plasoscaffolder/bll/templates/formatter_test_template.jinja2
plasoscaffolder/bll/templates/parser_init_template.jinja2
plasoscaffolder/bll/templates/parser_template.jinja2
plasoscaffolder/bll/templates/parser_test_template.jinja2
plasoscaffolder/common/__init__.py
plasoscaffolder/common/base_code_formatter.py
plasoscaffolder/common/base_file_handler.py
plasoscaffolder/common/base_output_handler.py
plasoscaffolder/common/code_formatter.py
plasoscaffolder/common/file_handler.py
plasoscaffolder/common/output_handler_click.py
plasoscaffolder/common/type_mapper.py
plasoscaffolder/dal/__init__.py
plasoscaffolder/dal/base_database_information.py
plasoscaffolder/dal/base_explain_query_plan.py
plasoscaffolder/dal/base_sql_query_execution.py
plasoscaffolder/dal/base_type_helper.py
plasoscaffolder-0.1.dist-info/DESCRIPTION.rst
plasoscaffolder-0.1.dist-info/METADATA
plasoscaffolder-0.1.dist-info/RECORD
plasoscaffolder-0.1.dist-info/WHEEL
plasoscaffolder-0.1.dist-info/entry_points.txt
plasoscaffolder-0.1.dist-info/metadata.json
plasoscaffolder-0.1.dist-info/top_level.txt
