Metadata-Version: 2.0
Name: plasoscaffolder
Version: 0.1
Summary: This is a scaffolder for sqlite plugins for plaso.
Home-page: http://plasoscaffolder.readthedocs.io
Author: Claudia Saxer
Author-email: UNKNOWN
License: UNKNOWN
Keywords: plaso scaffolder
Platform: UNKNOWN
Requires-Dist: Click (>=6.7)
Requires-Dist: colorama (>=0.3.7)
Requires-Dist: jinja2 (>=2.9.6)
Requires-Dist: pexpect (>=4.2.1)
Requires-Dist: setuptools (>=35.0.2)
Requires-Dist: yapf (==0.16.1)
